anonymizer.py
pcap_blur.py
algorithms/__init__.py
algorithms/black_marker.py
algorithms/permutation.py
algorithms/precision_degradation.py
algorithms/prefix_preserving_cryptopan.py
steps/__init__.py
steps/app_data.py
steps/checksum.py
steps/icmp.py
steps/ip_address.py
steps/mac_address.py
steps/port_numbers.py
steps/timestamps.py
utils/__init__.py
utils/check_tcp.py
utils/config.py
utils/validate.py
pcap_blur-2.0.1.dist-info/LICENSE.MD
pcap_blur-2.0.1.dist-info/METADATA
pcap_blur-2.0.1.dist-info/WHEEL
pcap_blur-2.0.1.dist-info/entry_points.txt
pcap_blur-2.0.1.dist-info/top_level.txt
pcap_blur-2.0.1.dist-info/RECORD
