Metadata-Version: 2.1
Name: pcap_blur
Version: 2.0.1
Summary: Pcap Blur is a command line tool that anonymizes network traffic.
Home-page: https://github.com/rafaelsilva81/pcap-blur
Author: Rafael Galdino da Silva
Author-email: rafaelgaldinosilva81@gmail.com
License: MIT
Classifier: Development Status :: 5 - Production/Stable
Classifier: Intended Audience :: Developers
Classifier: License :: OSI Approved :: MIT License
Classifier: Programming Language :: Python :: 3
Classifier: Topic :: Security
Classifier: Topic :: Security :: Cryptography
Classifier: Topic :: System :: Networking
Classifier: Topic :: Utilities
Requires-Python: >=3.10
License-File: LICENSE.MD
Requires-Dist: altgraph ==0.17.4
Requires-Dist: annotated-types ==0.6.0
Requires-Dist: anyio ==4.3.0
Requires-Dist: appdirs ==1.4.4
Requires-Dist: certifi ==2024.2.2
Requires-Dist: cffi ==1.16.0
Requires-Dist: click ==8.1.7
Requires-Dist: colorama ==0.4.6
Requires-Dist: cryptography ==42.0.7
Requires-Dist: dnspython ==2.6.1
Requires-Dist: email-validator ==2.1.1
Requires-Dist: fastapi ==0.111.0
Requires-Dist: fastapi-cli ==0.0.3
Requires-Dist: h11 ==0.14.0
Requires-Dist: httpcore ==1.0.5
Requires-Dist: httptools ==0.6.1
Requires-Dist: httpx ==0.27.0
Requires-Dist: idna ==3.7
Requires-Dist: Jinja2 ==3.1.4
Requires-Dist: line-profiler ==4.1.3
Requires-Dist: lxml ==5.2.1
Requires-Dist: markdown-it-py ==3.0.0
Requires-Dist: MarkupSafe ==2.1.5
Requires-Dist: mdurl ==0.1.2
Requires-Dist: memory-profiler ==0.61.0
Requires-Dist: orjson ==3.10.3
Requires-Dist: packaging ==24.0
Requires-Dist: pefile ==2023.2.7
Requires-Dist: picologging ==0.9.3
Requires-Dist: psutil ==5.9.8
Requires-Dist: py-spy ==0.3.14
Requires-Dist: pycparser ==2.22
Requires-Dist: pycryptodome ==3.20.0
Requires-Dist: pydantic ==2.7.1
Requires-Dist: pydantic-core ==2.18.2
Requires-Dist: Pygments ==2.18.0
Requires-Dist: pyinstaller ==6.5.0
Requires-Dist: pyinstaller-hooks-contrib ==2024.3
Requires-Dist: python-dotenv ==1.0.1
Requires-Dist: python-multipart ==0.0.9
Requires-Dist: pytz ==2024.1
Requires-Dist: pywin32-ctypes ==0.2.2
Requires-Dist: PyYAML ==6.0.1
Requires-Dist: rich ==13.7.1
Requires-Dist: scapy ==2.5.0
Requires-Dist: setuptools ==69.2.0
Requires-Dist: shellingham ==1.5.4
Requires-Dist: sniffio ==1.3.1
Requires-Dist: starlette ==0.37.2
Requires-Dist: termcolor ==2.4.0
Requires-Dist: typer ==0.12.3
Requires-Dist: typing-extensions ==4.11.0
Requires-Dist: tzdata ==2024.1
Requires-Dist: tzlocal ==5.2
Requires-Dist: ujson ==5.9.0
Requires-Dist: uvicorn ==0.29.0
Requires-Dist: watchfiles ==0.21.0
Requires-Dist: websockets ==12.0
Requires-Dist: yacryptopan ==1.0.1
